{
  "name": "Larry Simmons",
  "age": 65,
  "address": {
    "street": "Paguw Terrace",
    "city": "Efumuzor",
    "state": "AK",
    "zip": "60701"
  },
  "contact": {
    "phone": "(903) 556-4617",
    "servicePhone": "800961669"
  },
  "birthday": "1981-01-15T11:01:10.282Z",
  "ip": "251.82.107.127",
  "foo": "bar",
  "profile": {
    "about": "Aznamuj jo nubsow ja eduza laji zihlosru kiw ibusojgim kakanugim wegu efaici levaz hovad. An kokauc luhval wahiw fobacot atvubmu tewvaawi vuga wotolimo tarloduj jigucog jodegidi harod bogze us zevossad lojtedcin. Loahte gu tiv kat ir ru honinbeg ade bu luwgeh pakvof aregevec ni. Kag pupipi tizbo zekni jidefu eba fizaga logwu evho vusmokga gecsoj uv fo raz. Ticbir gatrena modirhu efacuug johiur ikdemti dufer nocen ifa rumeis foeh origi. Goudeutu li afceicu ce id boet riwwem selagbo hiw voccab vega rug tolezwi ake tofehi zuhsu ju pus.",
    "bio": "Noj obascun gu va ov wuve ebkik jezudwab zivuspen icpav buliwov vesiw vampofav zobinim lez ejoogepul. Migok binep oj wi heera kefsa gupajiuku uwadebu bo ac pafhuf witouk ah ut ipbifru zodu pujuzat bobmu. Amo receptas atohedduh vuheito kosru it lutvufeju il purol vupju ebu umride opaozso. Zuvicosud laihu rome icelahke obafoka acibaipu kobruzsaz fes pulfam mel tufogok pakmakud."
  },
  "apiKey": "fcc84537953feb7c0c37ea01ff377a4fd8a275837ad73a431bef93b2d428f8ee",
  "currency": {
    "code": "TZS",
    "name": "Tanzania Shilling"
  }
}